zgi/__init__.py
zgi/chat.py
zgi/client.py
zgi/files.py
zgi/fine_tuning.py
zgi/models.py
zgi/utils.py
zgiai-1.0.0.dist-info/licenses/LICENSE
zgiai-1.0.0.dist-info/METADATA
zgiai-1.0.0.dist-info/WHEEL
zgiai-1.0.0.dist-info/top_level.txt
zgiai-1.0.0.dist-info/RECORD
