Metadata-Version: 2.4
Name: zgiai
Version: 1.0.0
Summary: A lightweight utility library for modern Python development
Author-email: stark <stark@example.com>
License: MIT
Project-URL: Homepage, https://github.com/stark/zgi
Project-URL: Repository, https://github.com/stark/zgi
Project-URL: Issues, https://github.com/stark/zgi/issues
Keywords: zgi,utility,helper,toolkit,python,openai,ai,api
Classifier: Development Status :: 4 - Beta
Classifier: Intended Audience :: Developers
Classifier: License :: OSI Approved :: MIT License
Classifier: Programming Language :: Python :: 3
Classifier: Programming Language :: Python :: 3.7
Classifier: Programming Language :: Python :: 3.8
Classifier: Programming Language :: Python :: 3.9
Classifier: Programming Language :: Python :: 3.10
Classifier: Programming Language :: Python :: 3.11
Classifier: Programming Language :: Python :: 3.12
Requires-Python: >=3.7
License-File: LICENSE
Requires-Dist: requests>=2.20.0
Dynamic: license-file
Dynamic: requires-python
